pyopia/__init__.py
pyopia/auxillarydata.py
pyopia/background.py
pyopia/cf_metadata.json
pyopia/classify.py
pyopia/cli.py
pyopia/exampledata.py
pyopia/io.py
pyopia/metadata.py
pyopia/pipeline.py
pyopia/plotting.py
pyopia/process.py
pyopia/statistics.py
pyopia/dataexport/__init__.py
pyopia/dataexport/ecotaxa.py
pyopia/instrument/__init__.py
pyopia/instrument/common.py
pyopia/instrument/holo.py
pyopia/instrument/silcam.py
pyopia/instrument/uvp.py
pyopia/simulator/__init__.py
pyopia/simulator/silcam.py
pyopia/tests/__init__.py
pyopia/tests/test_auxillarydata.py
pyopia/tests/test_classify.py
pyopia/tests/test_io.py
pyopia/tests/test_notebooks.py
pyopia/tests/test_pipeline.py
pyopia-2.13.0.dist-info/METADATA
pyopia-2.13.0.dist-info/WHEEL
pyopia-2.13.0.dist-info/entry_points.txt
pyopia-2.13.0.dist-info/licenses/LICENSE
pyopia-2.13.0.dist-info/RECORD
