Metadata-Version: 2.4
Name: PyOPIA
Version: 2.13.0
Summary: A Python Ocean Particle Image Analysis toolbox.
Project-URL: Repository, https://github.com/sintef/pyopia
Project-URL: Documentation, https://pyopia.readthedocs.io
Author-email: Emlyn Davies <emlyn.davies@sintef.no>, "Alex Nimmo Smith@plymouth.ac.uk" <alex.nimmo.smith@plymouth.ac.uk>
License-File: LICENSE
Keywords: Imaging,Measurement,Ocean,Particles,Size distribution
Requires-Python: ~=3.12
Requires-Dist: click<8.2.0
Requires-Dist: cmocean<4,>=3.0.3
Requires-Dist: dask>=2024.8.1
Requires-Dist: flake8<7,>=6.1.0
Requires-Dist: gdown<5,>=4.7.1
Requires-Dist: h5netcdf>=1.3.0
Requires-Dist: h5py<4,>=3.9.0
Requires-Dist: imageio<3,>=2.31.3
Requires-Dist: ipykernel>=6.19.4
Requires-Dist: jupyter-book<0.16,>=0.15.1
Requires-Dist: matplotlib>=3.7
Requires-Dist: myst-nb<0.18,>=0.17.2
Requires-Dist: nbclient==0.7
Requires-Dist: nbconvert<8,>=7.16.4
Requires-Dist: numpy>=1.24.0
Requires-Dist: pandas[computation]<3,>=2.1.1
Requires-Dist: poetry-version-plugin<0.3,>=0.2.0
Requires-Dist: pydantic>=2.11.7
Requires-Dist: pytest-error-for-skips<3,>=2.0.2
Requires-Dist: pytest>=7.2.0
Requires-Dist: readthedocs-sphinx-search<0.4,>=0.3.2
Requires-Dist: scikit-image<0.25,>=0.24.0
Requires-Dist: scipy<2,>=1.11.2
Requires-Dist: seaborn>=0.13.2
Requires-Dist: sphinx-copybutton<0.6,>=0.5.2
Requires-Dist: sphinx-rtd-theme>=0.5.0
Requires-Dist: sphinx-togglebutton<0.4,>=0.3.2
Requires-Dist: sphinx==5.0
Requires-Dist: sphinxcontrib-napoleon>=0.7
Requires-Dist: toml<0.11,>=0.10.2
Requires-Dist: tqdm<5,>=4.66.1
Requires-Dist: typer[all]<0.10,>=0.9.0
Requires-Dist: urllib3<2.0
Requires-Dist: xarray<2024,>=2023.12.0
Provides-Extra: classification
Requires-Dist: keras==3.9.1; extra == 'classification'
Requires-Dist: tensorflow>=2.19.0; extra == 'classification'
